indigoAPI/__init__.py
indigoAPI-1.0.3.dist-info/LICENSE
indigoAPI-1.0.3.dist-info/METADATA
indigoAPI-1.0.3.dist-info/WHEEL
indigoAPI-1.0.3.dist-info/entry_points.txt
indigoAPI-1.0.3.dist-info/top_level.txt
indigoAPI-1.0.3.dist-info/RECORD
